flask_paycomuz/__init__.py
flask_paycomuz/decorators.py
flask_paycomuz/errors.py
flask_paycomuz/exeptions.py
flask_paycomuz/views.py
Flask_PaycomUz-1.2.5.dist-info/LICENCE
Flask_PaycomUz-1.2.5.dist-info/METADATA
Flask_PaycomUz-1.2.5.dist-info/WHEEL
Flask_PaycomUz-1.2.5.dist-info/top_level.txt
Flask_PaycomUz-1.2.5.dist-info/RECORD
