Metadata-Version: 2.1
Name: Flask-PaycomUz
Version: 1.2.5
Summary: Paycom.uz integration with Flask application, (only for Uzbekistan)
Home-page: https://github.com/Odya-LLC/flask_paycomuz
Author: odya
Author-email: mmuhtor@gmail.com
License: MIT
Platform: 3.6
Platform: 3.7
Platform: 3.8
Platform: 3.9
Platform: 3.10
Classifier: Environment :: Web Environment
Classifier: Intended Audience :: Developers
Classifier: License :: OSI Approved :: MIT License
Classifier: Operating System :: OS Independent
Classifier: Programming Language :: Python
Classifier: Topic :: Internet :: WWW/HTTP :: Dynamic Content
Classifier: Topic :: Software Development :: Libraries :: Python Modules
License-File: LICENCE
Requires-Dist: Flask
Requires-Dist: Flask-SQLAlchemy
